README.md
setup.py
config/__init__.py
config/config.py
config/models.py
confluence/__init__.py
confluence/confluence_client.py
confluence/context_node.py
confluence/html_cleaner.py
confluence/image_analyze.py
confluence/image_downloader.py
confluence/text_processor.py
database/__init__.py
database/chroma_manager.py
database/cosmos_service.py
embedding/__init__.py
embedding/embedding_manager.py
insightDocs.egg-info/PKG-INFO
insightDocs.egg-info/SOURCES.txt
insightDocs.egg-info/dependency_links.txt
insightDocs.egg-info/requires.txt
insightDocs.egg-info/top_level.txt
llm/__init__.py
llm/llm_manager.py
text_splitter/__init__.py
text_splitter/splitter.py