Metadata-Version: 2.1
Name: insightDocs
Version: 0.0.3
Summary: RAG
Author: devashish
Author-email: jadhavom263@gmail.com
Keywords: python,rag
Classifier: Development Status :: 3 - Alpha
Classifier: Intended Audience :: Developers
Classifier: Programming Language :: Python :: 2
Classifier: Programming Language :: Python :: 3
Classifier: Operating System :: MacOS :: MacOS X
Classifier: Operating System :: Microsoft :: Windows
